sm_tomusic_ai/__init__.py
sm_tomusic_ai-1767867.374.989.dist-info/licenses/LICENSE
sm_tomusic_ai-1767867.374.989.dist-info/METADATA
sm_tomusic_ai-1767867.374.989.dist-info/WHEEL
sm_tomusic_ai-1767867.374.989.dist-info/top_level.txt
sm_tomusic_ai-1767867.374.989.dist-info/RECORD
