Metadata-Version: 2.4
Name: sm-tomusic-ai
Version: 1767867.374.989
Summary: High-quality integration for https://tomusic.ai/
Home-page: https://tomusic.ai/
Author: SuperMaker
Classifier: Programming Language :: Python :: 3
Classifier: License :: OSI Approved :: MIT License
Requires-Python: >=3.6
License-File: LICENSE
Dynamic: author
Dynamic: classifier
Dynamic: description
Dynamic: description-content-type
Dynamic: home-page
Dynamic: license-file
Dynamic: requires-python
Dynamic: summary
